MRFPY/__init__.py
MRFPY/forecast.py
MRFPY/helper.py
MRFPY/modelSelection.py
MRFPY/rollingForecastingOrigin.py
MRFPY/wavelet.py
MRFPY/examples/entsoe.csv
MRFPY-1.0.1.dist-info/LICENSE
MRFPY-1.0.1.dist-info/METADATA
MRFPY-1.0.1.dist-info/WHEEL
MRFPY-1.0.1.dist-info/top_level.txt
MRFPY-1.0.1.dist-info/RECORD
