Metadata-Version: 2.1
Name: MRFPY
Version: 1.0.1
Summary: Timeseries forecasting with wavelets
Home-page: UNKNOWN
Author: Quirin Stier
Author-email: Quirin_Stier@gmx.de
License: UNKNOWN
Project-URL: R-Version, https://github.com/Quirinms/MRFR
Project-URL: Source, https://github.com/Quirinms/MRFPY
Platform: UNKNOWN
Classifier: Programming Language :: Python :: 3
Classifier: License :: OSI Approved :: MIT License
Classifier: Operating System :: OS Independent
Requires-Python: >=3.6
License-File: LICENSE
Requires-Dist: pandas (>=1.0.0)
Requires-Dist: numpy (>=1.16)
Requires-Dist: scipy (>=1.1.0)
Requires-Dist: scikit-learn (>=0.21.0)
